MANIFEST.in
setup.cfg
setup.py
graphframes/__init__.py
graphframes/graphframe.py
graphframes/tests.py
graphframes/examples/__init__.py
graphframes/examples/belief_propagation.py
graphframes/examples/graphs.py
graphframes/lib/__init__.py
graphframes/lib/aggregate_messages.py
graphframes/lib/pregel.py
graphframes_latest.egg-info/PKG-INFO
graphframes_latest.egg-info/SOURCES.txt
graphframes_latest.egg-info/dependency_links.txt
graphframes_latest.egg-info/requires.txt
graphframes_latest.egg-info/top_level.txt