Metadata-Version: 1.1
Name: graphframes-latest
Version: 0.8.3
Summary: GraphFrames: DataFrame-based Graphs
Home-page: https://github.com/graphframes/graphframes
Author: UNKNOWN
Author-email: UNKNOWN
License: MIT
Platform: UNKNOWN
Classifier: Development Status :: 3 - Alpha
Classifier: License :: OSI Approved :: MIT License
Classifier: Programming Language :: Python
